simple_alto_parser/VERSION
simple_alto_parser/__init__.py
simple_alto_parser/alto_file.py
simple_alto_parser/alto_file_exporter.py
simple_alto_parser/alto_file_parser.py
simple_alto_parser/base_parser.py
simple_alto_parser/dictionary_creator.py
simple_alto_parser/dictionary_parser.py
simple_alto_parser/nlp_parser.py
simple_alto_parser/pattern_parser.py
simple_alto_parser/utils.py
simple_alto_parser-0.0.22.dist-info/licenses/LICENSE
simple_alto_parser-0.0.22.dist-info/METADATA
simple_alto_parser-0.0.22.dist-info/WHEEL
simple_alto_parser-0.0.22.dist-info/top_level.txt
simple_alto_parser-0.0.22.dist-info/RECORD
