Metadata-Version: 2.4
Name: simple-alto-parser
Version: 0.0.22
Summary: A python module to read and parse ALTO files
Home-page: https://simple-alto-parser.readthedocs.io/en/latest/
Author: Sorin Marti, Lea Kasper
Author-email: sorin.marti@gmail.com, lea.kasper@unibas.ch
License: GPLv3
Classifier: Development Status :: 4 - Beta
Classifier: Intended Audience :: Education
Classifier: Intended Audience :: Science/Research
Classifier: License :: OSI Approved :: GNU General Public License v3 (GPLv3)
Classifier: Natural Language :: English
Classifier: Operating System :: OS Independent
Classifier: Programming Language :: Python
Classifier: Programming Language :: Python :: 3
Requires-Python: >=3.9
License-File: LICENSE
Requires-Dist: setuptools~=80.10.1
Dynamic: license-file
